<GladeWidgetClass>

  <Properties>

    <Property Id="minimum" Name="Min" Default="0">
      <Spec>glade_gtk_standard_float_spec</Spec>
      <SetFunction>glade_gtk_spin_button_set_min</SetFunction>
    </Property>
    <Property Id="maximum" Name="Max" Default="100">
      <Spec>glade_gtk_standard_float_spec</Spec>
      <SetFunction>glade_gtk_spin_button_set_max</SetFunction>
    </Property>
    <Property Id="step-increment" Name="Step Inc." Default="1">
      <Spec>glade_gtk_standard_float_spec</Spec>
      <SetFunction>glade_gtk_spin_button_set_step_increment</SetFunction>
    </Property>
    <Property Id="page-increment" Name="Page Inc." Default="10">
      <Spec>glade_gtk_standard_float_spec</Spec>
      <SetFunction>glade_gtk_spin_button_set_step_increment</SetFunction>
    </Property>
    <Property Id="page-size" Name="Page Size" Default="10">
      <Spec>glade_gtk_standard_float_spec</Spec>
      <SetFunction>glade_gtk_spin_button_set_step_increment</SetFunction>
    </Property>

  </Properties>

</GladeWidgetClass>
	 
	 
	     
